<?xml version='1.0' encoding='utf-8'?>
<TextureAtlas imagePath="Dukeanibo.png">
<SubTexture name="Dukeanibo Laugh0000" x="3702" y="4541" width="417" height="702" frameX="-48" frameY="-46" frameWidth="1000" frameHeight="1000" />
<SubTexture name="Dukeanibo Laugh0001" x="4119" y="4541" width="417" height="702" frameX="-48" frameY="-46" frameWidth="1000" frameHeight="1000" />
<SubTexture name="Dukeanibo Laugh0002" x="4119" y="4541" width="417" height="702" frameX="-48" frameY="-46" frameWidth="1000" frameHeight="1000" />
<SubTexture name="Dukeanibo Laugh0003" x="5923" y="0" width="465" height="690" frameX="-48" frameY="-58" frameWidth="1000" frameHeight="1000" />
<SubTexture name="Dukeanibo Laugh0004" x="5923" y="0" width="465" height="690" frameX="-48" frameY="-58" frameWidth="1000" frameHeight="1000" />
<SubTexture name="Dukeanibo Laugh0005" x="0" y="5286" width="477" height="672" frameX="-48" frameY="-76" frameWidth="1000" frameHeight="1000" />
<SubTexture name="Dukeanibo Laugh0006" x="0" y="5286" width="477" height="672" frameX="-48" frameY="-76" frameWidth="1000" frameHeight="1000" />
<SubTexture name="Dukeanibo Laugh0007" x="4915" y="745" width="423" height="729" frameX="-48" frameY="-19" frameWidth="1000" frameHeight="1000" />
<SubTexture name="Dukeanibo Laugh0008" x="4915" y="745" width="423" height="729" frameX="-48" frameY="-19" frameWidth="1000" frameHeight="1000" />
<SubTexture name="Dukeanibo Laugh0009" x="4915" y="2889" width="399" height="705" frameX="-48" frameY="-43" frameWidth="1000" frameHeight="1000" />
<SubTexture name="Dukeanibo Laugh0010" x="4915" y="2889" width="399" height="705" frameX="-48" frameY="-43" frameWidth="1000" frameHeight="1000" />
<SubTexture name="Dukeanibo Laugh0011" x="4956" y="4541" width="400" height="700" frameX="-48" frameY="-48" frameWidth="1000" frameHeight="1000" />
<SubTexture name="Dukeanibo Laugh0012" x="4956" y="4541" width="400" height="700" frameX="-48" frameY="-48" frameWidth="1000" frameHeight="1000" />
<SubTexture name="Dukeanibo Laugh0013" x="5523" y="0" width="400" height="691" frameX="-48" frameY="-57" frameWidth="1000" frameHeight="1000" />
<SubTexture name="Dukeanibo Laugh0014" x="5523" y="0" width="400" height="691" frameX="-48" frameY="-57" frameWidth="1000" frameHeight="1000" />
<SubTexture name="Dukeanibo Laugh0015" x="4915" y="2182" width="414" height="707" frameX="-48" frameY="-41" frameWidth="1000" frameHeight="1000" />
<SubTexture name="Dukeanibo Laugh0016" x="4915" y="2182" width="414" height="707" frameX="-48" frameY="-41" frameWidth="1000" frameHeight="1000" />
<SubTexture name="Dukeanibo Laugh0017" x="4915" y="3594" width="412" height="705" frameX="-48" frameY="-43" frameWidth="1000" frameHeight="1000" />
<SubTexture name="Dukeanibo Laugh0018" x="4915" y="3594" width="412" height="705" frameX="-48" frameY="-43" frameWidth="1000" frameHeight="1000" />
<SubTexture name="Dukeanibo Laugh0019" x="4915" y="2182" width="414" height="707" frameX="-48" frameY="-41" frameWidth="1000" frameHeight="1000" />
<SubTexture name="Dukeanibo Laugh0020" x="4915" y="2182" width="414" height="707" frameX="-48" frameY="-41" frameWidth="1000" frameHeight="1000" />
<SubTexture name="Dukeanibo Laugh0021" x="4915" y="3594" width="412" height="705" frameX="-48" frameY="-43" frameWidth="1000" frameHeight="1000" />
<SubTexture name="Dukeanibo Laugh0022" x="4915" y="3594" width="412" height="705" frameX="-48" frameY="-43" frameWidth="1000" frameHeight="1000" />
<SubTexture name="Dukeanibo Laugh0023" x="4915" y="2182" width="414" height="707" frameX="-48" frameY="-41" frameWidth="1000" frameHeight="1000" />
<SubTexture name="Dukeanibo Laugh0024" x="4915" y="2182" width="414" height="707" frameX="-48" frameY="-41" frameWidth="1000" frameHeight="1000" />
<SubTexture name="Dukeanibo Laugh0025" x="4915" y="3594" width="412" height="705" frameX="-48" frameY="-43" frameWidth="1000" frameHeight="1000" />
<SubTexture name="Dukeanibo Laugh0026" x="4915" y="3594" width="412" height="705" frameX="-48" frameY="-43" frameWidth="1000" frameHeight="1000" />
<SubTexture name="Dukeanibo Laugh0027" x="4915" y="2182" width="414" height="707" frameX="-48" frameY="-41" frameWidth="1000" frameHeight="1000" />
<SubTexture name="Dukeanibo Laugh0028" x="4915" y="2182" width="414" height="707" frameX="-48" frameY="-41" frameWidth="1000" frameHeight="1000" />
<SubTexture name="Dukeanibo Laugh0029" x="4915" y="3594" width="412" height="705" frameX="-48" frameY="-43" frameWidth="1000" frameHeight="1000" />
<SubTexture name="Dukeanibo Laugh0030" x="4915" y="3594" width="412" height="705" frameX="-48" frameY="-43" frameWidth="1000" frameHeight="1000" />
<SubTexture name="Dukeanibo Laugh0031" x="4915" y="2182" width="414" height="707" frameX="-48" frameY="-41" frameWidth="1000" frameHeight="1000" />
<SubTexture name="Dukeanibo Laugh0032" x="4915" y="2182" width="414" height="707" frameX="-48" frameY="-41" frameWidth="1000" frameHeight="1000" />
<SubTexture name="Dukeanibo Laugh0033" x="4915" y="3594" width="412" height="705" frameX="-48" frameY="-43" frameWidth="1000" frameHeight="1000" />
<SubTexture name="Dukeanibo Laugh0034" x="4915" y="3594" width="412" height="705" frameX="-48" frameY="-43" frameWidth="1000" frameHeight="1000" />
<SubTexture name="Dukeanibo Laugh0035" x="4915" y="2182" width="414" height="707" frameX="-48" frameY="-41" frameWidth="1000" frameHeight="1000" />
<SubTexture name="Dukeanibo Laugh0036" x="4915" y="2182" width="414" height="707" frameX="-48" frameY="-41" frameWidth="1000" frameHeight="1000" />
<SubTexture name="Dukeanibo Laugh0037" x="4915" y="3594" width="412" height="705" frameX="-48" frameY="-43" frameWidth="1000" frameHeight="1000" />
<SubTexture name="Dukeanibo Laugh0038" x="4915" y="3594" width="412" height="705" frameX="-48" frameY="-43" frameWidth="1000" frameHeight="1000" />
<SubTexture name="Dukeanibo Laugh0039" x="4915" y="2182" width="414" height="707" frameX="-48" frameY="-41" frameWidth="1000" frameHeight="1000" />
<SubTexture name="Dukeanibo Laugh0040" x="4915" y="2182" width="414" height="707" frameX="-48" frameY="-41" frameWidth="1000" frameHeight="1000" />
<SubTexture name="Dukeanibo Laugh0041" x="4915" y="3594" width="412" height="705" frameX="-48" frameY="-43" frameWidth="1000" frameHeight="1000" />
<SubTexture name="Dukeanibo Laugh0042" x="4915" y="3594" width="412" height="705" frameX="-48" frameY="-43" frameWidth="1000" frameHeight="1000" />
<SubTexture name="Dukeanibo Laugh0043" x="4915" y="2182" width="414" height="707" frameX="-48" frameY="-41" frameWidth="1000" frameHeight="1000" />
<SubTexture name="Dukeanibo Laugh0044" x="4915" y="2182" width="414" height="707" frameX="-48" frameY="-41" frameWidth="1000" frameHeight="1000" />
<SubTexture name="Dukeanibo Laugh0045" x="4915" y="3594" width="412" height="705" frameX="-48" frameY="-43" frameWidth="1000" frameHeight="1000" />
<SubTexture name="Dukeanibo Laugh0046" x="4915" y="3594" width="412" height="705" frameX="-48" frameY="-43" frameWidth="1000" frameHeight="1000" />
<SubTexture name="Dukeanibo Laugh0047" x="4915" y="2182" width="414" height="707" frameX="-48" frameY="-41" frameWidth="1000" frameHeight="1000" />
<SubTexture name="Dukeanibo Laugh0048" x="4915" y="2182" width="414" height="707" frameX="-48" frameY="-41" frameWidth="1000" frameHeight="1000" />
<SubTexture name="Dukeanibo Laugh0049" x="4915" y="3594" width="412" height="705" frameX="-48" frameY="-43" frameWidth="1000" frameHeight="1000" />
<SubTexture name="Dukeanibo Laugh0050" x="4915" y="3594" width="412" height="705" frameX="-48" frameY="-43" frameWidth="1000" frameHeight="1000" />
<SubTexture name="Dukeanibo Laugh0051" x="4915" y="2182" width="414" height="707" frameX="-48" frameY="-41" frameWidth="1000" frameHeight="1000" />
<SubTexture name="Dukeanibo Laugh0052" x="4915" y="2182" width="414" height="707" frameX="-48" frameY="-41" frameWidth="1000" frameHeight="1000" />
<SubTexture name="Dukeanibo Laugh0053" x="4915" y="3594" width="412" height="705" frameX="-48" frameY="-43" frameWidth="1000" frameHeight="1000" />
<SubTexture name="Dukeanibo Laugh0054" x="4915" y="3594" width="412" height="705" frameX="-48" frameY="-43" frameWidth="1000" frameHeight="1000" />
<SubTexture name="Dukeanibo Laugh0055" x="4915" y="2182" width="414" height="707" frameX="-48" frameY="-41" frameWidth="1000" frameHeight="1000" />
<SubTexture name="Dukeanibo Laugh0056" x="4915" y="2182" width="414" height="707" frameX="-48" frameY="-41" frameWidth="1000" frameHeight="1000" />
<SubTexture name="Dukeanibo Laugh0057" x="4915" y="3594" width="412" height="705" frameX="-48" frameY="-43" frameWidth="1000" frameHeight="1000" />
<SubTexture name="Dukeanibo Laugh0058" x="4915" y="3594" width="412" height="705" frameX="-48" frameY="-43" frameWidth="1000" frameHeight="1000" />
<SubTexture name="Dukeanibo Laugh0059" x="4915" y="2182" width="414" height="707" frameX="-48" frameY="-41" frameWidth="1000" frameHeight="1000" />
<SubTexture name="Dukeanibo Laugh0060" x="4915" y="2182" width="414" height="707" frameX="-48" frameY="-41" frameWidth="1000" frameHeight="1000" />
<SubTexture name="Dukeanibo Laugh0061" x="4915" y="3594" width="412" height="705" frameX="-48" frameY="-43" frameWidth="1000" frameHeight="1000" />
<SubTexture name="Dukeanibo Laugh0062" x="4915" y="3594" width="412" height="705" frameX="-48" frameY="-43" frameWidth="1000" frameHeight="1000" />
<SubTexture name="Dukeanibo Laugh0063" x="4915" y="2182" width="414" height="707" frameX="-48" frameY="-41" frameWidth="1000" frameHeight="1000" />
<SubTexture name="Dukeanibo Laugh0064" x="4915" y="2182" width="414" height="707" frameX="-48" frameY="-41" frameWidth="1000" frameHeight="1000" />
<SubTexture name="Dukeanibo Laugh0065" x="4915" y="3594" width="412" height="705" frameX="-48" frameY="-43" frameWidth="1000" frameHeight="1000" />
<SubTexture name="Dukeanibo Laugh0066" x="4915" y="3594" width="412" height="705" frameX="-48" frameY="-43" frameWidth="1000" frameHeight="1000" />
<SubTexture name="Dukeanibo Laugh0067" x="4915" y="2182" width="414" height="707" frameX="-48" frameY="-41" frameWidth="1000" frameHeight="1000" />
<SubTexture name="Dukeanibo Laugh0068" x="4915" y="2182" width="414" height="707" frameX="-48" frameY="-41" frameWidth="1000" frameHeight="1000" />
<SubTexture name="Dukeanibo Laugh0069" x="4915" y="3594" width="412" height="705" frameX="-48" frameY="-43" frameWidth="1000" frameHeight="1000" />
<SubTexture name="Dukeanibo Laugh0070" x="4915" y="3594" width="412" height="705" frameX="-48" frameY="-43" frameWidth="1000" frameHeight="1000" />
<SubTexture name="Dukeanibo Laugh0071" x="4915" y="2182" width="414" height="707" frameX="-48" frameY="-41" frameWidth="1000" frameHeight="1000" />
<SubTexture name="Dukeanibo Laugh0072" x="4915" y="2182" width="414" height="707" frameX="-48" frameY="-41" frameWidth="1000" frameHeight="1000" />
<SubTexture name="Dukeanibo Laugh0073" x="4915" y="3594" width="412" height="705" frameX="-48" frameY="-43" frameWidth="1000" frameHeight="1000" />
<SubTexture name="Dukeanibo Laugh0074" x="4915" y="3594" width="412" height="705" frameX="-48" frameY="-43" frameWidth="1000" frameHeight="1000" />
<SubTexture name="Dukeanibo Laugh0075" x="4334" y="3793" width="412" height="705" frameX="-48" frameY="-43" frameWidth="1000" frameHeight="1000" />
<SubTexture name="Dukeanibo Laugh0076" x="4334" y="3793" width="412" height="705" frameX="-48" frameY="-43" frameWidth="1000" frameHeight="1000" />
<SubTexture name="Dukeanibo Laugh0077" x="2464" y="4541" width="408" height="703" frameX="-48" frameY="-45" frameWidth="1000" frameHeight="1000" />
<SubTexture name="Dukeanibo Laugh0078" x="2464" y="4541" width="408" height="703" frameX="-48" frameY="-45" frameWidth="1000" frameHeight="1000" />
<SubTexture name="Dukeanibo Laugh0079" x="2872" y="4541" width="414" height="703" frameX="-48" frameY="-45" frameWidth="1000" frameHeight="1000" />
<SubTexture name="Dukeanibo Laugh0080" x="2872" y="4541" width="414" height="703" frameX="-48" frameY="-45" frameWidth="1000" frameHeight="1000" />
<SubTexture name="Dukeanibo Laugh0081" x="3286" y="4541" width="416" height="703" frameX="-48" frameY="-45" frameWidth="1000" frameHeight="1000" />
<SubTexture name="Dukeanibo Laugh0082" x="3286" y="4541" width="416" height="703" frameX="-48" frameY="-45" frameWidth="1000" frameHeight="1000" />
<SubTexture name="Dukeanibo Laugh0083" x="4915" y="1474" width="420" height="708" frameX="-48" frameY="-40" frameWidth="1000" frameHeight="1000" />
<SubTexture name="Dukeanibo Laugh0084" x="4915" y="1474" width="420" height="708" frameX="-48" frameY="-40" frameWidth="1000" frameHeight="1000" />
<SubTexture name="Dukeanibo Laugh0085" x="4536" y="4541" width="420" height="702" frameX="-48" frameY="-46" frameWidth="1000" frameHeight="1000" />
<SubTexture name="Dukeanibo Laugh0086" x="4536" y="4541" width="420" height="702" frameX="-48" frameY="-46" frameWidth="1000" frameHeight="1000" />
<SubTexture name="Dukeanibo Laugh0087" x="5923" y="690" width="403" height="669" frameX="-48" frameY="-79" frameWidth="1000" frameHeight="1000" />
<SubTexture name="Dukeanibo Laugh0088" x="5923" y="690" width="403" height="669" frameX="-48" frameY="-79" frameWidth="1000" frameHeight="1000" />
<SubTexture name="Dukeanibo Laugh0089" x="5923" y="1359" width="407" height="669" frameX="-48" frameY="-79" frameWidth="1000" frameHeight="1000" />
<SubTexture name="Dukeanibo Laugh0090" x="5923" y="1359" width="407" height="669" frameX="-48" frameY="-79" frameWidth="1000" frameHeight="1000" />
<SubTexture name="Dukeanibo Laugh0091" x="5923" y="2028" width="410" height="669" frameX="-48" frameY="-79" frameWidth="1000" frameHeight="1000" />
<SubTexture name="Dukeanibo Laugh0092" x="5923" y="2028" width="410" height="669" frameX="-48" frameY="-79" frameWidth="1000" frameHeight="1000" />
<SubTexture name="Dukeanibo Laugh0093" x="5923" y="2697" width="417" height="667" frameX="-46" frameY="-81" frameWidth="1000" frameHeight="1000" />
<SubTexture name="Dukeanibo Laugh0094" x="5923" y="3364" width="417" height="667" frameX="-46" frameY="-81" frameWidth="1000" frameHeight="1000" />
<SubTexture name="Dukeanibo Laugh0095" x="5923" y="4031" width="423" height="661" frameX="-46" frameY="-87" frameWidth="1000" frameHeight="1000" />
<SubTexture name="Dukeanibo Laugh0096" x="477" y="5286" width="422" height="661" frameX="-47" frameY="-87" frameWidth="1000" frameHeight="1000" />
<SubTexture name="Dukeanibo Laugh0097" x="899" y="5286" width="428" height="658" frameX="-47" frameY="-90" frameWidth="1000" frameHeight="1000" />
<SubTexture name="Dukeanibo Laugh0098" x="1327" y="5286" width="434" height="658" frameX="-41" frameY="-90" frameWidth="1000" frameHeight="1000" />
<SubTexture name="Dukeanibo Laugh0099" x="1761" y="5286" width="450" height="652" frameX="-41" frameY="-96" frameWidth="1000" frameHeight="1000" />
<SubTexture name="Dukeanibo Laugh0100" x="1761" y="5286" width="450" height="652" frameX="-41" frameY="-96" frameWidth="1000" frameHeight="1000" />
<SubTexture name="Dukeanibo Laugh0101" x="1761" y="5286" width="450" height="652" frameX="-41" frameY="-96" frameWidth="1000" frameHeight="1000" />
<SubTexture name="Dukeanibo Laugh0102" x="1761" y="5286" width="450" height="652" frameX="-41" frameY="-96" frameWidth="1000" frameHeight="1000" />
<SubTexture name="Dukeanibo Laugh0103" x="1761" y="5286" width="450" height="652" frameX="-41" frameY="-96" frameWidth="1000" frameHeight="1000" />
<SubTexture name="Dukeanibo Laugh0104" x="1761" y="5286" width="450" height="652" frameX="-41" frameY="-96" frameWidth="1000" frameHeight="1000" />
<SubTexture name="Dukeanibo Laugh0105" x="1761" y="5286" width="450" height="652" frameX="-41" frameY="-96" frameWidth="1000" frameHeight="1000" />
<SubTexture name="Dukeanibo Laugh0106" x="1761" y="5286" width="450" height="652" frameX="-41" frameY="-96" frameWidth="1000" frameHeight="1000" />
<SubTexture name="Dukeanibo Laugh0107" x="1761" y="5286" width="450" height="652" frameX="-41" frameY="-96" frameWidth="1000" frameHeight="1000" />
<SubTexture name="Dukeanibo Laugh0108" x="1761" y="5286" width="450" height="652" frameX="-41" frameY="-96" frameWidth="1000" frameHeight="1000" />
<SubTexture name="Dukeanibo Laugh0109" x="1761" y="5286" width="450" height="652" frameX="-41" frameY="-96" frameWidth="1000" frameHeight="1000" />
<SubTexture name="Dukeanibo Laugh0110" x="1761" y="5286" width="450" height="652" frameX="-41" frameY="-96" frameWidth="1000" frameHeight="1000" />
<SubTexture name="Dukeanibo Laugh0111" x="1761" y="5286" width="450" height="652" frameX="-41" frameY="-96" frameWidth="1000" frameHeight="1000" />
<SubTexture name="Dukeanibo Laugh0112" x="1761" y="5286" width="450" height="652" frameX="-41" frameY="-96" frameWidth="1000" frameHeight="1000" />
<SubTexture name="Dukeanibo Safe0000" x="3096" y="3040" width="648" height="751" frameX="-94" frameY="-133" frameWidth="1000" frameHeight="1250" />
<SubTexture name="Dukeanibo Safe0001" x="1242" y="764" width="611" height="762" frameX="-131" frameY="-122" frameWidth="1000" frameHeight="1250" />
<SubTexture name="Dukeanibo Safe0002" x="1242" y="764" width="611" height="762" frameX="-131" frameY="-122" frameWidth="1000" frameHeight="1250" />
<SubTexture name="Dukeanibo Safe0003" x="1863" y="0" width="584" height="759" frameX="-143" frameY="-125" frameWidth="1000" frameHeight="1250" />
<SubTexture name="Dukeanibo Safe0004" x="1863" y="759" width="584" height="759" frameX="-143" frameY="-125" frameWidth="1000" frameHeight="1250" />
<SubTexture name="Dukeanibo Safe0005" x="3744" y="3040" width="531" height="747" frameX="-174" frameY="-137" frameWidth="1000" frameHeight="1250" />
<SubTexture name="Dukeanibo Safe0006" x="3744" y="3040" width="531" height="747" frameX="-174" frameY="-137" frameWidth="1000" frameHeight="1250" />
<SubTexture name="Dukeanibo Safe0007" x="621" y="2285" width="562" height="753" frameX="-155" frameY="-131" frameWidth="1000" frameHeight="1250" />
<SubTexture name="Dukeanibo Safe0008" x="621" y="2285" width="562" height="753" frameX="-155" frameY="-131" frameWidth="1000" frameHeight="1250" />
<SubTexture name="Dukeanibo Safe0009" x="2447" y="1510" width="587" height="754" frameX="-144" frameY="-130" frameWidth="1000" frameHeight="1250" />
<SubTexture name="Dukeanibo Safe0010" x="2447" y="1510" width="587" height="754" frameX="-144" frameY="-130" frameWidth="1000" frameHeight="1250" />
<SubTexture name="Dukeanibo Safe0011" x="1225" y="1528" width="599" height="755" frameX="-142" frameY="-129" frameWidth="1000" frameHeight="1250" />
<SubTexture name="Dukeanibo Safe0012" x="1225" y="1528" width="599" height="755" frameX="-142" frameY="-129" frameWidth="1000" frameHeight="1250" />
<SubTexture name="Dukeanibo Safe0013" x="1824" y="1528" width="604" height="755" frameX="-137" frameY="-129" frameWidth="1000" frameHeight="1250" />
<SubTexture name="Dukeanibo Safe0014" x="1824" y="1528" width="604" height="755" frameX="-137" frameY="-129" frameWidth="1000" frameHeight="1250" />
<SubTexture name="Dukeanibo Safe0015" x="2447" y="0" width="607" height="755" frameX="-134" frameY="-129" frameWidth="1000" frameHeight="1250" />
<SubTexture name="Dukeanibo Safe0016" x="2447" y="0" width="607" height="755" frameX="-134" frameY="-129" frameWidth="1000" frameHeight="1250" />
<SubTexture name="Dukeanibo Safe0017" x="2447" y="755" width="607" height="755" frameX="-134" frameY="-129" frameWidth="1000" frameHeight="1250" />
<SubTexture name="Dukeanibo Safe0018" x="2447" y="755" width="607" height="755" frameX="-134" frameY="-129" frameWidth="1000" frameHeight="1250" />
<SubTexture name="Dukeanibo Safe0019" x="615" y="1528" width="610" height="756" frameX="-131" frameY="-128" frameWidth="1000" frameHeight="1250" />
<SubTexture name="Dukeanibo Safe0020" x="615" y="1528" width="610" height="756" frameX="-131" frameY="-128" frameWidth="1000" frameHeight="1250" />
<SubTexture name="Dukeanibo Safe0021" x="0" y="1528" width="615" height="757" frameX="-126" frameY="-127" frameWidth="1000" frameHeight="1250" />
<SubTexture name="Dukeanibo Safe0022" x="0" y="1528" width="615" height="757" frameX="-126" frameY="-127" frameWidth="1000" frameHeight="1250" />
<SubTexture name="Dukeanibo Safe0023" x="0" y="0" width="621" height="764" frameX="-120" frameY="-120" frameWidth="1000" frameHeight="1250" />
<SubTexture name="Dukeanibo Safe0024" x="0" y="0" width="621" height="764" frameX="-120" frameY="-120" frameWidth="1000" frameHeight="1250" />
<SubTexture name="Dukeanibo Safe0025" x="621" y="0" width="621" height="764" frameX="-120" frameY="-120" frameWidth="1000" frameHeight="1250" />
<SubTexture name="Dukeanibo Safe0026" x="621" y="0" width="621" height="764" frameX="-120" frameY="-120" frameWidth="1000" frameHeight="1250" />
<SubTexture name="Dukeanibo Safe0027" x="1242" y="0" width="621" height="764" frameX="-120" frameY="-120" frameWidth="1000" frameHeight="1250" />
<SubTexture name="Dukeanibo Safe0028" x="1242" y="0" width="621" height="764" frameX="-120" frameY="-120" frameWidth="1000" frameHeight="1250" />
<SubTexture name="Dukeanibo Safe0029" x="0" y="764" width="621" height="764" frameX="-120" frameY="-120" frameWidth="1000" frameHeight="1250" />
<SubTexture name="Dukeanibo Safe0030" x="0" y="764" width="621" height="764" frameX="-120" frameY="-120" frameWidth="1000" frameHeight="1250" />
<SubTexture name="Dukeanibo Safe0031" x="621" y="764" width="621" height="764" frameX="-120" frameY="-120" frameWidth="1000" frameHeight="1250" />
<SubTexture name="Dukeanibo Safe0032" x="621" y="764" width="621" height="764" frameX="-120" frameY="-120" frameWidth="1000" frameHeight="1250" />
<SubTexture name="Dukeanibo Safe0033" x="621" y="764" width="621" height="764" frameX="-120" frameY="-120" frameWidth="1000" frameHeight="1250" />
<SubTexture name="Dukeanibo Safe0034" x="621" y="764" width="621" height="764" frameX="-120" frameY="-120" frameWidth="1000" frameHeight="1250" />
<SubTexture name="Dukeanibo Safe0035" x="621" y="764" width="621" height="764" frameX="-120" frameY="-120" frameWidth="1000" frameHeight="1250" />
<SubTexture name="Dukeanibo Safe0036" x="621" y="764" width="621" height="764" frameX="-120" frameY="-120" frameWidth="1000" frameHeight="1250" />
<SubTexture name="Dukeanibo Safe0037" x="621" y="764" width="621" height="764" frameX="-120" frameY="-120" frameWidth="1000" frameHeight="1250" />
<SubTexture name="Dukeanibo Safe0038" x="621" y="764" width="621" height="764" frameX="-120" frameY="-120" frameWidth="1000" frameHeight="1250" />
<SubTexture name="Dukeanibo Safe0039" x="621" y="764" width="621" height="764" frameX="-120" frameY="-120" frameWidth="1000" frameHeight="1250" />
<SubTexture name="Dukeanibo Safe0040" x="621" y="764" width="621" height="764" frameX="-120" frameY="-120" frameWidth="1000" frameHeight="1250" />
<SubTexture name="Dukeanibo Safe0041" x="621" y="764" width="621" height="764" frameX="-120" frameY="-120" frameWidth="1000" frameHeight="1250" />
<SubTexture name="Dukeanibo Safe0042" x="621" y="764" width="621" height="764" frameX="-120" frameY="-120" frameWidth="1000" frameHeight="1250" />
<SubTexture name="Dukeanibo Safe0043" x="621" y="764" width="621" height="764" frameX="-120" frameY="-120" frameWidth="1000" frameHeight="1250" />
<SubTexture name="Dukeanibo Safe0044" x="621" y="764" width="621" height="764" frameX="-120" frameY="-120" frameWidth="1000" frameHeight="1250" />
<SubTexture name="Dukeanibo Safe0045" x="621" y="764" width="621" height="764" frameX="-120" frameY="-120" frameWidth="1000" frameHeight="1250" />
<SubTexture name="Dukeanibo Safe0046" x="621" y="764" width="621" height="764" frameX="-120" frameY="-120" frameWidth="1000" frameHeight="1250" />
<SubTexture name="Dukeanibo Safe0047" x="621" y="764" width="621" height="764" frameX="-120" frameY="-120" frameWidth="1000" frameHeight="1250" />
<SubTexture name="Dukeanibo Safe0048" x="621" y="764" width="621" height="764" frameX="-120" frameY="-120" frameWidth="1000" frameHeight="1250" />
<SubTexture name="Dukeanibo Safe0049" x="621" y="764" width="621" height="764" frameX="-120" frameY="-120" frameWidth="1000" frameHeight="1250" />
<SubTexture name="Dukeanibo Safe0050" x="621" y="764" width="621" height="764" frameX="-120" frameY="-120" frameWidth="1000" frameHeight="1250" />
<SubTexture name="Dukeanibo Safe0051" x="621" y="764" width="621" height="764" frameX="-120" frameY="-120" frameWidth="1000" frameHeight="1250" />
<SubTexture name="Dukeanibo Safe0052" x="621" y="764" width="621" height="764" frameX="-120" frameY="-120" frameWidth="1000" frameHeight="1250" />
<SubTexture name="Dukeanibo Safe0053" x="621" y="764" width="621" height="764" frameX="-120" frameY="-120" frameWidth="1000" frameHeight="1250" />
<SubTexture name="Dukeanibo Safe0054" x="621" y="764" width="621" height="764" frameX="-120" frameY="-120" frameWidth="1000" frameHeight="1250" />
<SubTexture name="Dukeanibo Safe0055" x="621" y="764" width="621" height="764" frameX="-120" frameY="-120" frameWidth="1000" frameHeight="1250" />
<SubTexture name="Dukeanibo Safe0056" x="621" y="764" width="621" height="764" frameX="-120" frameY="-120" frameWidth="1000" frameHeight="1250" />
<SubTexture name="Dukeanibo Safe0057" x="621" y="764" width="621" height="764" frameX="-120" frameY="-120" frameWidth="1000" frameHeight="1250" />
<SubTexture name="Dukeanibo Safe0058" x="621" y="764" width="621" height="764" frameX="-120" frameY="-120" frameWidth="1000" frameHeight="1250" />
<SubTexture name="Dukeanibo Safe0059" x="621" y="764" width="621" height="764" frameX="-120" frameY="-120" frameWidth="1000" frameHeight="1250" />
<SubTexture name="Dukeanibo Safe0060" x="621" y="764" width="621" height="764" frameX="-120" frameY="-120" frameWidth="1000" frameHeight="1250" />
<SubTexture name="Dukeanibo Safe0061" x="2484" y="3040" width="612" height="752" frameX="-129" frameY="-132" frameWidth="1000" frameHeight="1250" />
<SubTexture name="Dukeanibo Safe0062" x="0" y="2285" width="621" height="755" frameX="-120" frameY="-129" frameWidth="1000" frameHeight="1250" />
<SubTexture name="Dukeanibo Safe0063" x="0" y="2285" width="621" height="755" frameX="-120" frameY="-129" frameWidth="1000" frameHeight="1250" />
<SubTexture name="Dukeanibo Safe0064" x="4296" y="0" width="619" height="748" frameX="-122" frameY="-136" frameWidth="1000" frameHeight="1250" />
<SubTexture name="Dukeanibo Safe0065" x="4296" y="0" width="619" height="748" frameX="-122" frameY="-136" frameWidth="1000" frameHeight="1250" />
<SubTexture name="Dukeanibo Safe0066" x="4296" y="748" width="619" height="748" frameX="-122" frameY="-136" frameWidth="1000" frameHeight="1250" />
<SubTexture name="Dukeanibo Safe0067" x="4296" y="748" width="619" height="748" frameX="-122" frameY="-136" frameWidth="1000" frameHeight="1250" />
<SubTexture name="Dukeanibo Safe0068" x="4296" y="1496" width="619" height="748" frameX="-122" frameY="-136" frameWidth="1000" frameHeight="1250" />
<SubTexture name="Dukeanibo Safe0069" x="4296" y="1496" width="619" height="748" frameX="-122" frameY="-136" frameWidth="1000" frameHeight="1250" />
<SubTexture name="Dukeanibo Safe0070" x="4296" y="2244" width="619" height="748" frameX="-122" frameY="-136" frameWidth="1000" frameHeight="1250" />
<SubTexture name="Dukeanibo Safe0071" x="4296" y="2244" width="619" height="748" frameX="-122" frameY="-136" frameWidth="1000" frameHeight="1250" />
<SubTexture name="Dukeanibo Safe0072" x="4296" y="2992" width="619" height="748" frameX="-122" frameY="-136" frameWidth="1000" frameHeight="1250" />
<SubTexture name="Dukeanibo Safe0073" x="4296" y="2992" width="619" height="748" frameX="-122" frameY="-136" frameWidth="1000" frameHeight="1250" />
<SubTexture name="Dukeanibo Safe0074" x="0" y="3793" width="619" height="748" frameX="-122" frameY="-136" frameWidth="1000" frameHeight="1250" />
<SubTexture name="Dukeanibo Safe0075" x="0" y="3793" width="619" height="748" frameX="-122" frameY="-136" frameWidth="1000" frameHeight="1250" />
<SubTexture name="Dukeanibo Safe0076" x="619" y="3793" width="619" height="748" frameX="-122" frameY="-136" frameWidth="1000" frameHeight="1250" />
<SubTexture name="Dukeanibo Safe0077" x="619" y="3793" width="619" height="748" frameX="-122" frameY="-136" frameWidth="1000" frameHeight="1250" />
<SubTexture name="Dukeanibo Safe0078" x="1238" y="3793" width="619" height="748" frameX="-122" frameY="-136" frameWidth="1000" frameHeight="1250" />
<SubTexture name="Dukeanibo Safe0079" x="1238" y="3793" width="619" height="748" frameX="-122" frameY="-136" frameWidth="1000" frameHeight="1250" />
<SubTexture name="Dukeanibo Safe0080" x="1857" y="3793" width="619" height="748" frameX="-122" frameY="-136" frameWidth="1000" frameHeight="1250" />
<SubTexture name="Dukeanibo Safe0081" x="1857" y="3793" width="619" height="748" frameX="-122" frameY="-136" frameWidth="1000" frameHeight="1250" />
<SubTexture name="Dukeanibo Safe0082" x="1183" y="2285" width="621" height="753" frameX="-120" frameY="-131" frameWidth="1000" frameHeight="1250" />
<SubTexture name="Dukeanibo Safe0083" x="1183" y="2285" width="621" height="753" frameX="-120" frameY="-131" frameWidth="1000" frameHeight="1250" />
<SubTexture name="Dukeanibo Safe0084" x="1804" y="2285" width="621" height="753" frameX="-120" frameY="-131" frameWidth="1000" frameHeight="1250" />
<SubTexture name="Dukeanibo Safe0085" x="1804" y="2285" width="621" height="753" frameX="-120" frameY="-131" frameWidth="1000" frameHeight="1250" />
<SubTexture name="Dukeanibo Safe0086" x="2425" y="2285" width="621" height="753" frameX="-120" frameY="-131" frameWidth="1000" frameHeight="1250" />
<SubTexture name="Dukeanibo Safe0087" x="2425" y="2285" width="621" height="753" frameX="-120" frameY="-131" frameWidth="1000" frameHeight="1250" />
<SubTexture name="Dukeanibo Safe0088" x="3054" y="0" width="621" height="753" frameX="-120" frameY="-131" frameWidth="1000" frameHeight="1250" />
<SubTexture name="Dukeanibo Safe0089" x="3054" y="0" width="621" height="753" frameX="-120" frameY="-131" frameWidth="1000" frameHeight="1250" />
<SubTexture name="Dukeanibo Safe0090" x="3054" y="753" width="621" height="753" frameX="-120" frameY="-131" frameWidth="1000" frameHeight="1250" />
<SubTexture name="Dukeanibo Safe0091" x="3054" y="753" width="621" height="753" frameX="-120" frameY="-131" frameWidth="1000" frameHeight="1250" />
<SubTexture name="Dukeanibo Safe0092" x="2425" y="2285" width="621" height="753" frameX="-120" frameY="-131" frameWidth="1000" frameHeight="1250" />
<SubTexture name="Dukeanibo Safe0093" x="2425" y="2285" width="621" height="753" frameX="-120" frameY="-131" frameWidth="1000" frameHeight="1250" />
<SubTexture name="Dukeanibo Safe0094" x="2425" y="2285" width="621" height="753" frameX="-120" frameY="-131" frameWidth="1000" frameHeight="1250" />
<SubTexture name="Dukeanibo Safe0095" x="2425" y="2285" width="621" height="753" frameX="-120" frameY="-131" frameWidth="1000" frameHeight="1250" />
<SubTexture name="Dukeanibo Safe0096" x="3054" y="1506" width="621" height="753" frameX="-120" frameY="-131" frameWidth="1000" frameHeight="1250" />
<SubTexture name="Dukeanibo Safe0097" x="3054" y="1506" width="621" height="753" frameX="-120" frameY="-131" frameWidth="1000" frameHeight="1250" />
<SubTexture name="Dukeanibo Safe0098" x="1183" y="2285" width="621" height="753" frameX="-120" frameY="-131" frameWidth="1000" frameHeight="1250" />
<SubTexture name="Dukeanibo Safe0099" x="1183" y="2285" width="621" height="753" frameX="-120" frameY="-131" frameWidth="1000" frameHeight="1250" />
<SubTexture name="Dukeanibo Safe0100" x="3054" y="2259" width="621" height="753" frameX="-120" frameY="-131" frameWidth="1000" frameHeight="1250" />
<SubTexture name="Dukeanibo Safe0101" x="3054" y="2259" width="621" height="753" frameX="-120" frameY="-131" frameWidth="1000" frameHeight="1250" />
<SubTexture name="Dukeanibo Safe0102" x="3054" y="753" width="621" height="753" frameX="-120" frameY="-131" frameWidth="1000" frameHeight="1250" />
<SubTexture name="Dukeanibo Safe0103" x="3054" y="753" width="621" height="753" frameX="-120" frameY="-131" frameWidth="1000" frameHeight="1250" />
<SubTexture name="Dukeanibo Safe0104" x="3675" y="0" width="621" height="753" frameX="-120" frameY="-131" frameWidth="1000" frameHeight="1250" />
<SubTexture name="Dukeanibo Safe0105" x="3675" y="0" width="621" height="753" frameX="-120" frameY="-131" frameWidth="1000" frameHeight="1250" />
<SubTexture name="Dukeanibo Safe0106" x="3675" y="0" width="621" height="753" frameX="-120" frameY="-131" frameWidth="1000" frameHeight="1250" />
<SubTexture name="Dukeanibo Safe0107" x="3675" y="753" width="621" height="753" frameX="-120" frameY="-131" frameWidth="1000" frameHeight="1250" />
<SubTexture name="Dukeanibo Safe0108" x="3675" y="1506" width="621" height="753" frameX="-120" frameY="-131" frameWidth="1000" frameHeight="1250" />
<SubTexture name="Dukeanibo Safe0109" x="3675" y="2259" width="621" height="753" frameX="-120" frameY="-131" frameWidth="1000" frameHeight="1250" />
<SubTexture name="Dukeanibo Safe0110" x="0" y="3040" width="621" height="753" frameX="-120" frameY="-131" frameWidth="1000" frameHeight="1250" />
<SubTexture name="Dukeanibo Safe0111" x="621" y="3040" width="621" height="753" frameX="-120" frameY="-131" frameWidth="1000" frameHeight="1250" />
<SubTexture name="Dukeanibo Safe0112" x="1242" y="3040" width="621" height="753" frameX="-120" frameY="-131" frameWidth="1000" frameHeight="1250" />
<SubTexture name="Dukeanibo Safe0113" x="1863" y="3040" width="621" height="753" frameX="-120" frameY="-131" frameWidth="1000" frameHeight="1250" />
<SubTexture name="Dukeanibo Safe0114" x="2476" y="3793" width="625" height="745" frameX="-128" frameY="-139" frameWidth="1000" frameHeight="1250" />
<SubTexture name="Dukeanibo Safe0115" x="3101" y="3793" width="625" height="745" frameX="-128" frameY="-139" frameWidth="1000" frameHeight="1250" />
<SubTexture name="Dukeanibo Safe0116" x="3726" y="3793" width="608" height="745" frameX="-128" frameY="-139" frameWidth="1000" frameHeight="1250" />
<SubTexture name="Dukeanibo Safe0117" x="4915" y="0" width="608" height="745" frameX="-128" frameY="-139" frameWidth="1000" frameHeight="1250" />
<SubTexture name="Dukeanibo Safe0118" x="0" y="4541" width="616" height="745" frameX="-128" frameY="-139" frameWidth="1000" frameHeight="1250" />
<SubTexture name="Dukeanibo Safe0119" x="616" y="4541" width="616" height="745" frameX="-128" frameY="-139" frameWidth="1000" frameHeight="1250" />
<SubTexture name="Dukeanibo Safe0120" x="616" y="4541" width="616" height="745" frameX="-128" frameY="-139" frameWidth="1000" frameHeight="1250" />
<SubTexture name="Dukeanibo Safe0121" x="616" y="4541" width="616" height="745" frameX="-128" frameY="-139" frameWidth="1000" frameHeight="1250" />
<SubTexture name="Dukeanibo Safe0122" x="616" y="4541" width="616" height="745" frameX="-128" frameY="-139" frameWidth="1000" frameHeight="1250" />
<SubTexture name="Dukeanibo Safe0123" x="1232" y="4541" width="616" height="745" frameX="-128" frameY="-139" frameWidth="1000" frameHeight="1250" />
<SubTexture name="Dukeanibo Safe0124" x="1232" y="4541" width="616" height="745" frameX="-128" frameY="-139" frameWidth="1000" frameHeight="1250" />
<SubTexture name="Dukeanibo Safe0125" x="1848" y="4541" width="616" height="745" frameX="-128" frameY="-139" frameWidth="1000" frameHeight="1250" />
<SubTexture name="Dukeanibo Safe0126" x="1848" y="4541" width="616" height="745" frameX="-128" frameY="-139" frameWidth="1000" frameHeight="1250" />
<SubTexture name="Dukeanibo Safe0127" x="1848" y="4541" width="616" height="745" frameX="-128" frameY="-139" frameWidth="1000" frameHeight="1250" />
<SubTexture name="Dukeanibo Safe0128" x="1848" y="4541" width="616" height="745" frameX="-128" frameY="-139" frameWidth="1000" frameHeight="1250" />
<SubTexture name="Dukeanibo Safe0129" x="1848" y="4541" width="616" height="745" frameX="-128" frameY="-139" frameWidth="1000" frameHeight="1250" />
<SubTexture name="Dukeanibo Safe0130" x="1848" y="4541" width="616" height="745" frameX="-128" frameY="-139" frameWidth="1000" frameHeight="1250" />
<SubTexture name="Dukeanibo Safe0131" x="1848" y="4541" width="616" height="745" frameX="-128" frameY="-139" frameWidth="1000" frameHeight="1250" />
<SubTexture name="Dukeanibo Safe0132" x="1848" y="4541" width="616" height="745" frameX="-128" frameY="-139" frameWidth="1000" frameHeight="1250" />
<SubTexture name="Dukeanibo Safe0133" x="1848" y="4541" width="616" height="745" frameX="-128" frameY="-139" frameWidth="1000" frameHeight="1250" />
<SubTexture name="Dukeanibo Safe0134" x="1848" y="4541" width="616" height="745" frameX="-128" frameY="-139" frameWidth="1000" frameHeight="1250" />
<SubTexture name="Dukeanibo Safe0135" x="1848" y="4541" width="616" height="745" frameX="-128" frameY="-139" frameWidth="1000" frameHeight="1250" />
<SubTexture name="Dukeanibo Safe0136" x="1848" y="4541" width="616" height="745" frameX="-128" frameY="-139" frameWidth="1000" frameHeight="1250" />
<SubTexture name="Dukeanibo Safe0137" x="1848" y="4541" width="616" height="745" frameX="-128" frameY="-139" frameWidth="1000" frameHeight="1250" />
<SubTexture name="Dukeanibo Safe0138" x="1848" y="4541" width="616" height="745" frameX="-128" frameY="-139" frameWidth="1000" frameHeight="1250" />
<SubTexture name="Dukeanibo Safe0139" x="1848" y="4541" width="616" height="745" frameX="-128" frameY="-139" frameWidth="1000" frameHeight="1250" />
<SubTexture name="Dukeanibo Safe0140" x="1848" y="4541" width="616" height="745" frameX="-128" frameY="-139" frameWidth="1000" frameHeight="1250" />
<SubTexture name="Dukeanibo Safe0141" x="1848" y="4541" width="616" height="745" frameX="-128" frameY="-139" frameWidth="1000" frameHeight="1250" />
<SubTexture name="Dukeanibo Safe0142" x="1848" y="4541" width="616" height="745" frameX="-128" frameY="-139" frameWidth="1000" frameHeight="1250" />
<SubTexture name="Dukeanibo Safe0143" x="1848" y="4541" width="616" height="745" frameX="-128" frameY="-139" frameWidth="1000" frameHeight="1250" />
<SubTexture name="Dukeanibo Safe0144" x="1848" y="4541" width="616" height="745" frameX="-128" frameY="-139" frameWidth="1000" frameHeight="1250" />
<SubTexture name="Dukeanibo Safe0145" x="1848" y="4541" width="616" height="745" frameX="-128" frameY="-139" frameWidth="1000" frameHeight="1250" />
<SubTexture name="Dukeanibo Safe0146" x="1848" y="4541" width="616" height="745" frameX="-128" frameY="-139" frameWidth="1000" frameHeight="1250" />
<SubTexture name="Dukeanibo Safe0147" x="1848" y="4541" width="616" height="745" frameX="-128" frameY="-139" frameWidth="1000" frameHeight="1250" />
<SubTexture name="Dukeanibo Safe0148" x="1848" y="4541" width="616" height="745" frameX="-128" frameY="-139" frameWidth="1000" frameHeight="1250" />
<SubTexture name="Dukeanibo Safe0149" x="1848" y="4541" width="616" height="745" frameX="-128" frameY="-139" frameWidth="1000" frameHeight="1250" />
<SubTexture name="Dukeanibo Safe0150" x="1848" y="4541" width="616" height="745" frameX="-128" frameY="-139" frameWidth="1000" frameHeight="1250" />
<SubTexture name="Dukeanibo Safe0151" x="1848" y="4541" width="616" height="745" frameX="-128" frameY="-139" frameWidth="1000" frameHeight="1250" />
<SubTexture name="Dukeanibo Safe0152" x="1848" y="4541" width="616" height="745" frameX="-128" frameY="-139" frameWidth="1000" frameHeight="1250" />
<SubTexture name="Dukeanibo Safe0153" x="1848" y="4541" width="616" height="745" frameX="-128" frameY="-139" frameWidth="1000" frameHeight="1250" />
<SubTexture name="Dukeanibo Safe0154" x="1848" y="4541" width="616" height="745" frameX="-128" frameY="-139" frameWidth="1000" frameHeight="1250" />
<SubTexture name="Dukeanibo Safe0155" x="1848" y="4541" width="616" height="745" frameX="-128" frameY="-139" frameWidth="1000" frameHeight="1250" />
<SubTexture name="Dukeanibo Safe0156" x="1848" y="4541" width="616" height="745" frameX="-128" frameY="-139" frameWidth="1000" frameHeight="1250" />
<SubTexture name="Dukeanibo Safe0157" x="1848" y="4541" width="616" height="745" frameX="-128" frameY="-139" frameWidth="1000" frameHeight="1250" />
<SubTexture name="Dukeanibo Safe0158" x="1848" y="4541" width="616" height="745" frameX="-128" frameY="-139" frameWidth="1000" frameHeight="1250" />
<SubTexture name="Dukeanibo Safe0159" x="1848" y="4541" width="616" height="745" frameX="-128" frameY="-139" frameWidth="1000" frameHeight="1250" />
<SubTexture name="Dukeanibo Safe0160" x="1848" y="4541" width="616" height="745" frameX="-128" frameY="-139" frameWidth="1000" frameHeight="1250" />
<SubTexture name="Dukeanibo Safe0161" x="1848" y="4541" width="616" height="745" frameX="-128" frameY="-139" frameWidth="1000" frameHeight="1250" />
<SubTexture name="Dukeanibo Safe0162" x="1848" y="4541" width="616" height="745" frameX="-128" frameY="-139" frameWidth="1000" frameHeight="1250" />
<SubTexture name="Dukeanibo Safe0163" x="1848" y="4541" width="616" height="745" frameX="-128" frameY="-139" frameWidth="1000" frameHeight="1250" />
<SubTexture name="Dukeanibo Safe0164" x="1848" y="4541" width="616" height="745" frameX="-128" frameY="-139" frameWidth="1000" frameHeight="1250" />
<SubTexture name="Dukeanibo Safe0165" x="1848" y="4541" width="616" height="745" frameX="-128" frameY="-139" frameWidth="1000" frameHeight="1250" />
<SubTexture name="Dukeanibo Safe0166" x="1848" y="4541" width="616" height="745" frameX="-128" frameY="-139" frameWidth="1000" frameHeight="1250" />
<SubTexture name="Dukeanibo Safe0167" x="1848" y="4541" width="616" height="745" frameX="-128" frameY="-139" frameWidth="1000" frameHeight="1250" />
<SubTexture name="Dukeanibo Safe0168" x="1848" y="4541" width="616" height="745" frameX="-128" frameY="-139" frameWidth="1000" frameHeight="1250" />
<SubTexture name="Dukeanibo Safe0169" x="1848" y="4541" width="616" height="745" frameX="-128" frameY="-139" frameWidth="1000" frameHeight="1250" />
<SubTexture name="Dukeanibo Safe0170" x="1848" y="4541" width="616" height="745" frameX="-128" frameY="-139" frameWidth="1000" frameHeight="1250" />
<SubTexture name="Dukeanibo Safe0171" x="1848" y="4541" width="616" height="745" frameX="-128" frameY="-139" frameWidth="1000" frameHeight="1250" />
<SubTexture name="Dukeanibo Safe0172" x="1848" y="4541" width="616" height="745" frameX="-128" frameY="-139" frameWidth="1000" frameHeight="1250" />
<SubTexture name="Dukeanibo Safe0173" x="1848" y="4541" width="616" height="745" frameX="-128" frameY="-139" frameWidth="1000" frameHeight="1250" />
<SubTexture name="Dukeanibo Safe0174" x="1848" y="4541" width="616" height="745" frameX="-128" frameY="-139" frameWidth="1000" frameHeight="1250" />
<SubTexture name="Dukeanibo Safe0175" x="1848" y="4541" width="616" height="745" frameX="-128" frameY="-139" frameWidth="1000" frameHeight="1250" />
<SubTexture name="Dukeanibo Safe0176" x="1848" y="4541" width="616" height="745" frameX="-128" frameY="-139" frameWidth="1000" frameHeight="1250" />
<SubTexture name="Dukeanibo Safe0177" x="1848" y="4541" width="616" height="745" frameX="-128" frameY="-139" frameWidth="1000" frameHeight="1250" />
<SubTexture name="Dukeanibo Safe0178" x="1848" y="4541" width="616" height="745" frameX="-128" frameY="-139" frameWidth="1000" frameHeight="1250" />
<SubTexture name="Dukeanibo Safe0179" x="1848" y="4541" width="616" height="745" frameX="-128" frameY="-139" frameWidth="1000" frameHeight="1250" />
<SubTexture name="Dukeanibo Safe0180" x="1848" y="4541" width="616" height="745" frameX="-128" frameY="-139" frameWidth="1000" frameHeight="1250" />
<SubTexture name="Dukeanibo Safe0181" x="1848" y="4541" width="616" height="745" frameX="-128" frameY="-139" frameWidth="1000" frameHeight="1250" />
<SubTexture name="Dukeanibo Safe0182" x="1848" y="4541" width="616" height="745" frameX="-128" frameY="-139" frameWidth="1000" frameHeight="1250" />
<SubTexture name="Dukeanibo Safe0183" x="1848" y="4541" width="616" height="745" frameX="-128" frameY="-139" frameWidth="1000" frameHeight="1250" />
<SubTexture name="Dukeanibo Safe0184" x="1848" y="4541" width="616" height="745" frameX="-128" frameY="-139" frameWidth="1000" frameHeight="1250" />
<SubTexture name="Dukeanibo Safe0185" x="1848" y="4541" width="616" height="745" frameX="-128" frameY="-139" frameWidth="1000" frameHeight="1250" />
<SubTexture name="Dukeanibo Safe0186" x="1848" y="4541" width="616" height="745" frameX="-128" frameY="-139" frameWidth="1000" frameHeight="1250" />
<SubTexture name="Dukeanibo Safe0187" x="1848" y="4541" width="616" height="745" frameX="-128" frameY="-139" frameWidth="1000" frameHeight="1250" />
<SubTexture name="Dukeanibo Safe0188" x="1848" y="4541" width="616" height="745" frameX="-128" frameY="-139" frameWidth="1000" frameHeight="1250" />
<SubTexture name="Dukeanibo Safe0189" x="1848" y="4541" width="616" height="745" frameX="-128" frameY="-139" frameWidth="1000" frameHeight="1250" />
<SubTexture name="Dukeanibo Safe0190" x="1848" y="4541" width="616" height="745" frameX="-128" frameY="-139" frameWidth="1000" frameHeight="1250" />
<SubTexture name="Dukeanibo Safe0191" x="1848" y="4541" width="616" height="745" frameX="-128" frameY="-139" frameWidth="1000" frameHeight="1250" />
</TextureAtlas>
